alter/__init__.py
alter/_base_client.py
alter/_client.py
alter/_constants.py
alter/_exceptions.py
alter/_models.py
alter/_response.py
alter/_types.py
alter/_version.py
alter/resources/__init__.py
alter/resources/_base.py
alter/resources/health.py
alter/resources/mcp.py
alter/types/__init__.py
alter/types/health.py
alter_py-0.2.1.dist-info/METADATA
alter_py-0.2.1.dist-info/WHEEL
alter_py-0.2.1.dist-info/licenses/LICENSE
alter_py-0.2.1.dist-info/RECORD
