Metadata-Version: 2.4
Name: alter-py
Version: 0.2.1
Summary: The official Python client for the Alter AI API
Project-URL: Homepage, https://github.com/alter-ai/alter-py
Project-URL: Repository, https://github.com/alter-ai/alter-py
Project-URL: Documentation, https://docs.alter.ai
Project-URL: Issues, https://github.com/alter-ai/alter-py/issues
Author-email: Alter AI <dev@alter.ai>
License: MIT License
License-File: LICENSE
Classifier: Development Status :: 3 - Alpha
Classifier: Intended Audience :: Developers
Classifier: License :: OSI Approved :: MIT License
Classifier: Programming Language :: Python :: 3
Classifier: Programming Language :: Python :: 3.11
Classifier: Programming Language :: Python :: 3.12
Classifier: Typing :: Typed
Requires-Python: <3.14,>=3.9
Requires-Dist: anyio<5,>=3.5.0
Requires-Dist: distro<2,>=1.7.0
Requires-Dist: httpx<1,>=0.23.0
Requires-Dist: pydantic[email]<3,>=2.7.0
Requires-Dist: sniffio
Requires-Dist: typing-extensions<5,>=4.10.0
Provides-Extra: dev
Requires-Dist: dirty-equals>=0.6.0; extra == 'dev'
Requires-Dist: mypy>=1.5.1; extra == 'dev'
Requires-Dist: pytest-asyncio>=0.23.7; extra == 'dev'
Requires-Dist: pytest-cov>=4.0.0; extra == 'dev'
Requires-Dist: pytest>=8.1.2; extra == 'dev'
Requires-Dist: respx>=0.20.0; extra == 'dev'
Requires-Dist: rich>=13.7.1; extra == 'dev'
Requires-Dist: ruff>=0.4.0; extra == 'dev'
Requires-Dist: time-machine>=2.10.0; extra == 'dev'
